README.md
setup.py
bin/openai-ft
bin/openai-ft-classification
bin/openai-ft-events
bin/openai-ft-report
openai_finetune/__init__.py
openai_finetune/cli.py
openai_finetune/data_streams.py
openai_finetune/data_streams_test.py
openai_finetune/encoding.py
openai_finetune/event_logger.py
openai_finetune/events_cli.py
openai_finetune/load_dataset.py
openai_finetune/local_events_cache.py
openai_finetune/local_metadata_store.py
openai_finetune/planner.py
openai_finetune/report_cli.py
openai_finetune/train.py
openai_finetune/version.py
openai_finetune.egg-info/PKG-INFO
openai_finetune.egg-info/SOURCES.txt
openai_finetune.egg-info/dependency_links.txt
openai_finetune.egg-info/requires.txt
openai_finetune.egg-info/top_level.txt