Metadata-Version: 1.2
Name: openai-finetune
Version: 0.0.2rc0
Summary: Python client library for the OpenAI Fine-tuning API
Home-page: https://github.com/openai/openai-finetune
Author: OpenAI
Author-email: support@openai.com
License: UNKNOWN
Platform: UNKNOWN
Requires-Python: >=3.6
